LICENSE.txt
README.md
pyproject.toml
setup.cfg
setup.py
src/comm_f2py.f90
src/covariance.f90
src/filters.f90
src/subspace.f90
src/signal_subspace/__init__.py
src/signal_subspace/filter.py
src/signal_subspace/importfort.py
src/signal_subspace/plots.py
src/signal_subspace.egg-info/PKG-INFO
src/signal_subspace.egg-info/SOURCES.txt
src/signal_subspace.egg-info/dependency_links.txt
src/signal_subspace.egg-info/not-zip-safe
src/signal_subspace.egg-info/requires.txt
src/signal_subspace.egg-info/top_level.txt